{"is_source_file": true, "format": "Dart", "description": "This file defines a custom Flutter widget named RetroHeader, which is a stateless widget extending PreferredSizeWidget. It creates a styled AppBar with a gradient background, customizable title, subtitle, and optional actions.", "external_files": ["package:flutter/material.dart"], "external_methods": ["Theme.of", "Theme.of(context).colorScheme", "Theme.of(context).textTheme.bodySmall?.copyWith", "Size.fromHeight"], "published": ["RetroHeader"], "classes": [{"name": "RetroHeader", "description": "A custom app bar widget with gradient background, large height, and customizable title, subtitle, and actions."}], "methods": [{"name": "preferredSize", "description": "Returns the preferred size of the header, fixed at 86 height units."}, {"name": "build", "description": "Constructs the widget tree for the RetroHeader, including styling and layout."}], "calls": ["Theme.of(context)", "Theme.of(context).colorScheme", "Theme.of(context).textTheme.bodySmall?.copyWith", "Size.fromHeight(86)"], "search-terms": ["RetroHeader", "custom AppBar Flutter", "preferredSizeWidget", "gradient AppBar Flutter", "stateless widget Flutter"], "state": 2, "file_id": 31, "knowledge_revision": 66, "git_revision": "", "hash": "a84001dcbc7ea429065923585f0e21ad", "format-version": 4, "code-base-name": "recipe_app_frontend", "filename": "recipe_app_frontend/lib/src/ui/widgets/retro_header.dart", "revision_history": [{"66": ""}]}